mypackage/__init__.py
mypackage/__main__.py
mypackage/decorators.py
mypackage/descriptors.py
mypackage/generators.py
mypackage/iterators.py
mypackage_manqust-0.1.dist-info/METADATA
mypackage_manqust-0.1.dist-info/WHEEL
mypackage_manqust-0.1.dist-info/top_level.txt
mypackage_manqust-0.1.dist-info/RECORD
